LICENSE
README.md
setup.cfg
setup.py
stograde/__init__.py
stograde.egg-info/PKG-INFO
stograde.egg-info/SOURCES.txt
stograde.egg-info/dependency_links.txt
stograde.egg-info/entry_points.txt
stograde.egg-info/requires.txt
stograde.egg-info/top_level.txt
stograde/common/__init__.py
stograde/common/cat.py
stograde/common/chdir.py
stograde/common/dirsize.py
stograde/common/find_unmerged_branches_in_cwd.py
stograde/common/flatten.py
stograde/common/get_modification_time.py
stograde/common/group_by.py
stograde/common/modification_time.py
stograde/common/parse_commit_msg_for_assignments.py
stograde/common/pipe.py
stograde/common/run.py
stograde/common/run_status.py
stograde/common/version.py
stograde/drive/__init__.py
stograde/drive/drive.py
stograde/drive/drive_result.py
stograde/formatters/__init__.py
stograde/formatters/base.py
stograde/formatters/format_type.py
stograde/formatters/formatted_result.py
stograde/formatters/group_type.py
stograde/formatters/html.py
stograde/formatters/html_template.py
stograde/formatters/markdown.py
stograde/formatters/tabulate.py
stograde/formatters/truncate.py
stograde/process_assignment/__init__.py
stograde/process_assignment/assignment_status.py
stograde/process_assignment/assignment_type.py
stograde/process_assignment/process_assignment.py
stograde/process_assignment/record_result.py
stograde/process_assignment/submission_warnings.py
stograde/process_assignment/supporting.py
stograde/process_assignment/warning_unmerged_branches.py
stograde/process_file/__init__.py
stograde/process_file/compile_result.py
stograde/process_file/file_result.py
stograde/process_file/process_file.py
stograde/process_file/test_result.py
stograde/referee/__init__.py
stograde/referee/__main__.py
stograde/referee/args.py
stograde/referee/emailify.py
stograde/referee/parse_commits.py
stograde/referee/process_student.py
stograde/referee/send_email.py
stograde/specs/__init__.py
stograde/specs/download_specs.py
stograde/specs/file_options.py
stograde/specs/filter_specs.py
stograde/specs/load.py
stograde/specs/spec.py
stograde/specs/spec_file.py
stograde/specs/spec_repos.py
stograde/specs/stogradeignore.py
stograde/specs/supporting_file.py
