Metadata-Version: 1.1
Name: stograde
Version: 4.3.0
Summary: The StoGrade Toolkit
Home-page: https://github.com/stodevx/stograde
Author: Hawken Rives
Author-email: hawkrives@gmail.com
License: MIT
Keywords: stolaf course-tooling
Platform: UNKNOWN
Classifier: Development Status :: 4 - Beta
Classifier: Intended Audience :: Developers
Classifier: Topic :: Software Development :: Build Tools
Classifier: License :: OSI Approved :: MIT License
Classifier: Programming Language :: Python :: 3
Classifier: Programming Language :: Python :: 3.6
Classifier: Programming Language :: Python :: 3.7
Classifier: Programming Language :: Python :: 3.8
